Metadata-Version: 2.1
Name: sentry-ldap-auth-fix
Version: 2.8.3
Summary: A Sentry extension to add an LDAP server as an authentication source.
Home-page: https://github.com/BuSHari/getsentry-ldap-auth-fix
Author: Chad Killingsworth <chad.killingsworth@banno.com>, Barron Hagerman <barron.hagerman@banno.com>
Author-email: chad.killingsworth@banno.com
License: Apache-2.0
Download-URL: https://github.com/BuSHari/getsentry-ldap-auth-fix/releases/tag/2.8.3
Platform: UNKNOWN
Classifier: Framework :: Django
Classifier: Intended Audience :: Developers
Classifier: Intended Audience :: System Administrators
Classifier: Operating System :: OS Independent
Classifier: Topic :: Software Development
